pydvlp_docs/__init__.py
pydvlp_docs/autofix.py
pydvlp_docs/build_error_classifier.py
pydvlp_docs/build_monitor.py
pydvlp_docs/builders.py
pydvlp_docs/cli.py
pydvlp_docs/cli_config_consolidation.py
pydvlp_docs/cli_refactor.py
pydvlp_docs/commands.py
pydvlp_docs/config.py
pydvlp_docs/config_debug.py
pydvlp_docs/config_discovery.py
pydvlp_docs/display.py
pydvlp_docs/general_setup.py
pydvlp_docs/hooks.py
pydvlp_docs/interactive.py
pydvlp_docs/link_builder.py
pydvlp_docs/mock_operations.py
pydvlp_docs/package_auditor.py
pydvlp_docs/package_handlers.py
pydvlp_docs/smart_builder.py
pydvlp_docs/sphinx_debug.py
pydvlp_docs/template_manager.py
pydvlp_docs/templates/Makefile
pydvlp_docs/templates/_autoapi_templates/index.rst
pydvlp_docs/templates/_autoapi_templates/python/attribute.rst
pydvlp_docs/templates/_autoapi_templates/python/class.rst
pydvlp_docs/templates/_autoapi_templates/python/data.rst
pydvlp_docs/templates/_autoapi_templates/python/exception.rst
pydvlp_docs/templates/_autoapi_templates/python/function.rst
pydvlp_docs/templates/_autoapi_templates/python/method.rst
pydvlp_docs/templates/_autoapi_templates/python/module.rst
pydvlp_docs/templates/_autoapi_templates/python/package.rst
pydvlp_docs/templates/_autoapi_templates/python/property.rst
pydvlp_docs/templates/_autoapi_templates_BROKEN_BACKUP/python/_base/foundation.j2
pydvlp_docs/templates/_autoapi_templates_BROKEN_BACKUP/python/_base/progressive.j2
pydvlp_docs/templates/_autoapi_templates_BROKEN_BACKUP/python/_components/code_blocks.j2
pydvlp_docs/templates/_autoapi_templates_BROKEN_BACKUP/python/_components/diagrams.j2
pydvlp_docs/templates/_autoapi_templates_BROKEN_BACKUP/python/_components/navigation.j2
pydvlp_docs/templates/_autoapi_templates_BROKEN_BACKUP/python/_components/tooltips.j2
pydvlp_docs/templates/_autoapi_templates_BROKEN_BACKUP/python/_filters/__init__.py
pydvlp_docs/templates/_autoapi_templates_BROKEN_BACKUP/python/_filters/type_filters.py
pydvlp_docs-0.1.3.dist-info/METADATA
pydvlp_docs-0.1.3.dist-info/WHEEL
pydvlp_docs-0.1.3.dist-info/entry_points.txt
pydvlp_docs-0.1.3.dist-info/RECORD
